requestsockets/__init__.py
requestsockets/errors.py
requestsockets/socketrequests_.py
requestsockets/socketsession.py
requestsockets/test.py
requestsockets/types_.py
requestsockets/utils.py
requestsockets-0.0.2.dist-info/LICENSE
requestsockets-0.0.2.dist-info/METADATA
requestsockets-0.0.2.dist-info/WHEEL
requestsockets-0.0.2.dist-info/top_level.txt
requestsockets-0.0.2.dist-info/RECORD
