Metadata-Version: 2.1
Name: requestsockets
Version: 0.0.2
Summary: A http request library made using sockets
Author: Issac
Keywords: python,web surface,web scrape,http request,requests,sockets
Classifier: Development Status :: 1 - Planning
Classifier: Intended Audience :: Developers
Classifier: Programming Language :: Python :: 3
Classifier: Operating System :: Unix
Classifier: Operating System :: MacOS :: MacOS X
Classifier: Operating System :: Microsoft :: Windows
License-File: LICENSE
